pyzdoc/__init__.py
pyzdoc/constants.py
pyzdoc/zdoc.dll
pyzdoc-2024.4.29.dist-info/LICENSE
pyzdoc-2024.4.29.dist-info/METADATA
pyzdoc-2024.4.29.dist-info/WHEEL
pyzdoc-2024.4.29.dist-info/top_level.txt
pyzdoc-2024.4.29.dist-info/RECORD
